COPYING
assets/logo.png
assets/mo/it/LC_MESSAGES/com.gkayaalp.pomodorino.mo
assets/mo/tr/LC_MESSAGES/com.gkayaalp.pomodorino.mo
assets/pomodorino.desktop
pomodorino/__init__.py
pomodorino/app.py
pomodorino/common.py
pomodorino/indicator.py
pomodorino/settingsmodal.py
pomodorino-0.1.0b1.dist-info/entry_points.txt
pomodorino-0.1.0b1.dist-info/COPYING
pomodorino-0.1.0b1.dist-info/WHEEL
pomodorino-0.1.0b1.dist-info/METADATA
pomodorino-0.1.0b1.dist-info/RECORD
