Metadata-Version: 2.1
Name: pomodorino
Version: 0.1.0b1
Summary: Simple Pomodoro Timer
Home-page: https://www.gkayaalp.com/pomodorino.html
License: GPL-3.0+
Author: Göktuğ Kayaalp
Author-email: self@gkayaalp.com
Requires-Python: >=3.5,<4.0
Classifier: Development Status :: 3 - Alpha
Classifier: Environment :: X11 Applications :: Gnome
Classifier: Intended Audience :: End Users/Desktop
Classifier: License :: OSI Approved :: GNU General Public License v3 or later (GPLv3+)
Classifier: Programming Language :: Python :: 3
Classifier: Programming Language :: Python :: 3.5
Classifier: Programming Language :: Python :: 3.6
Classifier: Programming Language :: Python :: 3.7
Classifier: Topic :: Office/Business :: Scheduling
Classifier: Topic :: Utilities
Requires-Dist: PyGObject (>=3.34,<4.0)
Requires-Dist: dbus-python (>=1.2,<2.0)
Requires-Dist: notify2 (>=0.3.1,<0.4.0)
Requires-Dist: pycairo (>=1.18,<2.0)
Project-URL: Repository, https://github.com/cadadr/pomodorino
